setup.py
gcontext/__init__.py
gcontext/base.py
gcontext/hooks.py
gcontext/util.py
gcontext.egg-info/PKG-INFO
gcontext.egg-info/SOURCES.txt
gcontext.egg-info/dependency_links.txt
gcontext.egg-info/requires.txt
gcontext.egg-info/top_level.txt