Metadata-Version: 1.1
Name: gcontext
Version: 0.1
Summary: The global context in use.
Home-page: https://github.com/abetkin/gcontext
Author: abetkin
Author-email: abvit89@gmail.com
License: MIT
Keywords: global context threadlocal
Platform: UNKNOWN
Classifier: Development Status :: 3 - Alpha
Classifier: Intended Audience :: Developers
Classifier: Programming Language :: Python :: 3.3
Classifier: Programming Language :: Python :: 3.4
